odoo/addons/sale_order_report_without_price/README.rst
odoo/addons/sale_order_report_without_price/__init__.py
odoo/addons/sale_order_report_without_price/__manifest__.py
odoo/addons/sale_order_report_without_price/i18n/sale_order_report_without_price.pot
odoo/addons/sale_order_report_without_price/readme/CONTRIBUTORS.rst
odoo/addons/sale_order_report_without_price/readme/DESCRIPTION.rst
odoo/addons/sale_order_report_without_price/readme/USAGE.rst
odoo/addons/sale_order_report_without_price/report/sale_report.xml
odoo/addons/sale_order_report_without_price/report/sale_report_templates.xml
odoo/addons/sale_order_report_without_price/static/description/icon.png
odoo/addons/sale_order_report_without_price/static/description/index.html
odoo14_addon_sale_order_report_without_price-14.0.1.0.1.dist-info/METADATA
odoo14_addon_sale_order_report_without_price-14.0.1.0.1.dist-info/WHEEL
odoo14_addon_sale_order_report_without_price-14.0.1.0.1.dist-info/top_level.txt
odoo14_addon_sale_order_report_without_price-14.0.1.0.1.dist-info/RECORD
